[{"name":"7 Timeframe","status":"in_progress"},{"name":"30 Timeframe","status":"in_progress"},{"name":"7 Timeframe","status":"in_progress"},{"name":"7 Timeframe","status":"completed"},{"name":"30 Timeframe","status":"completed"},{"name":"90 Timeframe","status":"completed"},{"name":"30 Timeframe","status":"completed"},{"name":"7 Timeframe","status":"completed"},{"name":"90 Timeframe","status":"completed"},{"name":"30 Timeframe","status":"completed"},{"name":"7 Timeframe","status":"completed"},{"name":"90 Timeframe","status":"completed"},{"name":"7 Timeframe","status":"completed"},{"name":"30 Timeframe","status":"completed"},{"name":"90 Timeframe","status":"completed"},{"name":"30 Timeframe","status":"completed"},{"name":"7 Timeframe","status":"completed"},{"name":"90 Timeframe","status":"completed"},{"name":"90 Timeframe","status":"completed"},{"name":"30 Timeframe","status":"completed"},{"name":"7 Timeframe","status":"completed"},{"name":"30 Timeframe","status":"completed"},{"name":"90 Timeframe","status":"completed"},{"name":"7 Timeframe","status":"completed"},{"name":"90 Timeframe","status":"completed"},{"name":"90 Timeframe","status":"completed"},{"name":"7 Timeframe","status":"completed"},{"name":"30 Timeframe","status":"completed"},{"name":"90 Timeframe","status":"completed"},{"name":"90 Timeframe","status":"completed"},{"name":"90 Timeframe","status":"completed"},{"name":"90 Timeframe","status":"completed"},{"name":"90 Timeframe","status":"completed"},{"name":"90 Timeframe","status":"completed"},{"name":"90 Timeframe","status":"completed"},{"name":"90 Timeframe","status":"completed"},{"name":"90 Timeframe","status":"completed"},{"name":"90 Timeframe","status":"completed"},{"name":"90 Timeframe","status":"completed"},{"name":"90 Timeframe","status":"completed"},{"name":"90 Timeframe","status":"completed"},{"name":"90 Timeframe","status":"completed"},{"name":"90 Timeframe","status":"completed"},{"name":"90 Timeframe","status":"completed"},{"name":"90 Timeframe","status":"completed"},{"name":"90 Timeframe","status":"completed"},{"name":"90 Timeframe","status":"completed"},{"name":"90 Timeframe","status":"completed"},{"name":"90 Timeframe","status":"completed"},{"name":"90 Timeframe","status":"completed"},{"name":"90 Timeframe","status":"completed"},{"name":"90 Timeframe","status":"completed"},{"name":"90 Timeframe","status":"completed"},{"name":"90 Timeframe","status":"completed"},{"name":"90 Timeframe","status":"completed"},{"name":"90 Timeframe","status":"completed"},{"name":"7 Timeframe","status":"completed"},{"name":"30 Timeframe","status":"completed"},{"name":"90 Timeframe","status":"completed"},{"name":"90 Timeframe","status":"completed"},{"name":"90 Timeframe","status":"completed"},{"name":"90 Timeframe","status":"completed"},{"name":"90 Timeframe","status":"completed"},{"name":"90 Timeframe","status":"completed"},{"name":"90 Timeframe","status":"completed"},{"name":"90 Timeframe","status":"completed"},{"name":"90 Timeframe","status":"completed"},{"name":"90 Timeframe","status":"completed"},{"name":"90 Timeframe","status":"completed"},{"name":"90 Timeframe","status":"completed"},{"name":"7 Timeframe","status":"completed"},{"name":"90 Timeframe","status":"completed"},{"name":"30 Timeframe","status":"completed"},{"name":"90 Timeframe","status":"completed"},{"name":"90 Timeframe","status":"completed"},{"name":"90 Timeframe","status":"completed"},{"name":"90 Timeframe","status":"completed"},{"name":"90 Timeframe","status":"completed"},{"name":"30 Timeframe","status":"completed"},{"name":"90 Timeframe","status":"completed"},{"name":"90 Timeframe","status":"completed"},{"name":"30 Timeframe","status":"completed"},{"name":"90 Timeframe","status":"completed"},{"name":"90 Timeframe","status":"completed"},{"name":"90 Timeframe","status":"completed"},{"name":"90 Timeframe","status":"completed"},{"name":"30 Timeframe","status":"completed"},{"name":"7 Timeframe","status":"completed"},{"name":"30 Timeframe","status":"completed"},{"name":"90 Timeframe","status":"completed"},{"name":"90 Timeframe","status":"completed"},{"name":"7 Timeframe","status":"completed"},{"name":"30 Timeframe","status":"completed"},{"name":"90 Timeframe","status":"completed"},{"name":"90 Timeframe","status":"completed"},{"name":"90 Timeframe","status":"completed"},{"name":"7 Timeframe","status":"completed"},{"name":"30 Timeframe","status":"completed"},{"name":"30 Timeframe","status":"completed"},{"name":"90 Timeframe","status":"completed"}]
